pyEX/caching/__init__.py
pyEX/caching/_version.py
pyEX.caching-0.0.3.dist-info/LICENSE
pyEX.caching-0.0.3.dist-info/METADATA
pyEX.caching-0.0.3.dist-info/WHEEL
pyEX.caching-0.0.3.dist-info/top_level.txt
pyEX.caching-0.0.3.dist-info/RECORD
